{
  "derivative": {
    "patterns": {
      "^(differentiate|diff|derivative)([ ]+of)?[ ]+(.+)[ ]+(by[ ]+(.+))$": [
        "3",
        "5"
      ],
      "^(differentiate|diff|derivative)([ ]+of)?([ ]+(?!by))(.+)$": [
        "4"
      ]
    },
    "keywords": [
      "differentiate",
      "diff",
      "derivative"
    ]
  },
  "domain": {
    "patterns": {
      "^(domain|definition[ ]+(area|range))([ ]+of)?[ ]+(.+)$": [
        "4"
      ]
    },
    "keywords": [
      "domain",
      "definition",
      "area",
      "range"
    ]
  },
  "range": {
    "patterns": {
      "^(range)([ ]+of)?[ ]+(.+)$": [
        "3"
      ]
    },
    "keywords": [
      "range"
    ]
  },
  "zeros": {
    "patterns": {
      "^(zeros|zeroes)([ ]+of)?[ ]+(.+)$": [
        "3"
      ]
    },
    "keywords": [
      "zeros",
      "zeroes"
    ]
  },
  "axes_intersection": {
    "patterns": {
      "^intersect(ion)?([ ]+with)?[ ]+axes([ ]+of)?[ ]+(.+)$": [
        "4"
      ],
      "^axes[ ]+intersect(ion)?([ ]+of)?[ ]+(.+)$": [
        "3"
      ],
      "^axes[ ]+(.+)$": [
        "1"
      ]
    },
    "keywords": [
      "axes",
      "intersect",
      "intersection"
    ]
  },
  "periodicity": {
    "patterns": {
      "^period(icity)?([ ]+of)?[ ]+(.+)$": [
        "3"
      ]
    },
    "keywords": [
      "period",
      "periodicity"
    ]
  },
  "convexity": {
    "patterns": {
      "^convex(ity)?([ ]+of)?[ ]+(.+)$": [
        "3"
      ]
    },
    "keywords": [
      "convex",
      "convexity"
    ]
  },
  "concavity": {
    "patterns": {
      "^concav((e)|(ity))([ ]+of)?[ ]+(.+)$": [
        "5"
      ]
    },
    "keywords": [
      "concave",
      "concavity"
    ]
  },
  "continuity": {
    "patterns": {
      "^continu(ity|ous)([ ]+of)?[ ]+(.+)$": [
        "3"
      ]
    },
    "keywords": [
      "continuity",
      "continuous"
    ]
  },
  "vertical asymptotes": {
    "patterns": {
      "^(vertical|v)[ ]+asymptote(s)?([ ]+of)?[ ]+(.+)$": [
        "4"
      ]
    },
    "keywords": [
      "vertical"
    ]
  },
  "horizontal asymptotes": {
    "patterns": {
      "^(horizontal|h)[ ]+asymptote(s)?([ ]+of)?[ ]+(.+)$": [
        "4"
      ]
    },
    "keywords": [
      "horizontal"
    ]
  },
  "slant asymptotes": {
    "patterns": {
      "^(slant|s)[ ]+asymptote(s)?([ ]+of)?[ ]+(.+)$": [
        "4"
      ]
    },
    "keywords": [
      "slant",
      "asymptote",
      "asymptotes"
    ]
  },
  "asymptotes": {
    "patterns": {
      "^asymptote(s)?([ ]+of)?[ ]+(.+)$": [
        "3"
      ]
    },
    "keywords": [
      "asymptote",
      "asymptotes"
    ]
  },
  "evenness": {
    "patterns": {
      "^even(ness)?([ ]+of)?[ ]+(.+)$": [
        "3"
      ],
      "^is[ ]+(.+)[ ]+even([ ]*[?])?$": [
        "1"
      ]
    },
    "keywords": [
      "even",
      "evenness"
    ]
  },
  "oddness": {
    "patterns": {
      "^odd(ness)?([ ]+of)?[ ]+(.+)$": [
        "3"
      ],
      "^is[ ]+(.+)[ ]+odd([ ]*[?])?$": [
        "1"
      ]
    },
    "keywords": [
      "odd",
      "oddness"
    ]
  },
  "maximum": {
    "patterns": {
      "^max(imum)?([ ]+value)?([ ]+of)?[ ]+(.+)$": [
        "4"
      ],
      "^highest([ ]+value)?([ ]+of)?[ ]+(.+)$": [
        "3"
      ]
    },
    "keywords": [
      "max",
      "maximum",
      "highest",
      "value"
    ]
  },
  "minimum": {
    "patterns": {
      "^min(imum)?([ ]+value)?([ ]+of)?[ ]+(.+)$": [
        "4"
      ],
      "^(lowest|smallest)([ ]+value)?([ ]+of)?[ ]+(.+)$": [
        "4"
      ]
    },
    "keywords": [
      "min",
      "minimum",
      "lowest",
      "smallest"
    ]
  },
  "stationary points": {
    "patterns": {
      "^(crit(ical)?|stationary)([ ]+points)?([ ]+of)?[ ]+(.+)$": [
        "5"
      ]
    },
    "keywords": [
      "crit",
      "critical",
      "stationary"
    ]
  }
}